toolspec/__init__.py
toolspec/agent.lst
toolspec/binning.py
toolspec/fitting.py
toolspec/ini.cfg
toolspec/measure.py
toolspec/mining.py
toolspec/scorecard.py
toolspec/service.py
toolspec/util.py
toolspec-0.0.7.dist-info/METADATA
toolspec-0.0.7.dist-info/WHEEL
toolspec-0.0.7.dist-info/licenses/LICENSE
toolspec-0.0.7.dist-info/RECORD
