Metadata-Version: 2.1
Name: toolspec
Version: 0.0.7
Summary: This package may not run properly.
Author-email: Xiaoqing Chen <1092640727@qq.com>
License-File: LICENSE
Classifier: License :: OSI Approved :: MIT License
Classifier: Operating System :: OS Independent
Classifier: Programming Language :: Python :: 3
Requires-Python: >=3.7
